odoo8_addon_sale_order_weight-8.0.1.0.0.99.dev12-py3.8-nspkg.pth
odoo_addons/sale_order_weight/README.rst
odoo_addons/sale_order_weight/__init__.py
odoo_addons/sale_order_weight/__openerp__.py
odoo_addons/sale_order_weight/i18n/ca.po
odoo_addons/sale_order_weight/i18n/de.po
odoo_addons/sale_order_weight/i18n/el_GR.po
odoo_addons/sale_order_weight/i18n/es.po
odoo_addons/sale_order_weight/i18n/es_ES.po
odoo_addons/sale_order_weight/i18n/es_VE.po
odoo_addons/sale_order_weight/i18n/fi.po
odoo_addons/sale_order_weight/i18n/fr.po
odoo_addons/sale_order_weight/i18n/hr.po
odoo_addons/sale_order_weight/i18n/hr_HR.po
odoo_addons/sale_order_weight/i18n/hu.po
odoo_addons/sale_order_weight/i18n/id.po
odoo_addons/sale_order_weight/i18n/it.po
odoo_addons/sale_order_weight/i18n/nl.po
odoo_addons/sale_order_weight/i18n/nl_NL.po
odoo_addons/sale_order_weight/i18n/pt.po
odoo_addons/sale_order_weight/i18n/pt_BR.po
odoo_addons/sale_order_weight/i18n/ro.po
odoo_addons/sale_order_weight/i18n/sale_order_weight.pot
odoo_addons/sale_order_weight/i18n/sk.po
odoo_addons/sale_order_weight/i18n/sl.po
odoo_addons/sale_order_weight/i18n/tr.po
odoo_addons/sale_order_weight/i18n/tr_TR.po
odoo_addons/sale_order_weight/i18n/vi_VN.po
odoo_addons/sale_order_weight/i18n/zh_CN.po
odoo_addons/sale_order_weight/models/__init__.py
odoo_addons/sale_order_weight/models/sale_order.py
odoo_addons/sale_order_weight/static/description/icon.png
odoo_addons/sale_order_weight/tests/__init__.py
odoo_addons/sale_order_weight/tests/test_sale_order_weight.py
odoo_addons/sale_order_weight/views/sale_report.xml
odoo8_addon_sale_order_weight-8.0.1.0.0.99.dev12.dist-info/METADATA
odoo8_addon_sale_order_weight-8.0.1.0.0.99.dev12.dist-info/WHEEL
odoo8_addon_sale_order_weight-8.0.1.0.0.99.dev12.dist-info/namespace_packages.txt
odoo8_addon_sale_order_weight-8.0.1.0.0.99.dev12.dist-info/top_level.txt
odoo8_addon_sale_order_weight-8.0.1.0.0.99.dev12.dist-info/RECORD
